LICENSE
MANIFEST.in
README.md
requirements.txt
setup.cfg
setup.py
src/__init__.py
src/__pycache__/__init__.cpython-38.pyc
src/demand_forecast_source/__init__.py
src/demand_forecast_source.egg-info/PKG-INFO
src/demand_forecast_source.egg-info/SOURCES.txt
src/demand_forecast_source.egg-info/dependency_links.txt
src/demand_forecast_source.egg-info/requires.txt
src/demand_forecast_source.egg-info/top_level.txt
src/demand_forecast_source/__pycache__/__init__.cpython-38.pyc
src/demand_forecast_source/data/.gitkeep
src/demand_forecast_source/data/__init__.py
src/demand_forecast_source/data/split_dataset.py
src/demand_forecast_source/data/__pycache__/__init__.cpython-38.pyc
src/demand_forecast_source/data/__pycache__/split_dataset.cpython-38.pyc
src/demand_forecast_source/download/__init__.py
src/demand_forecast_source/download/download_from_s3.py
src/demand_forecast_source/entities/feature_params.py
src/demand_forecast_source/entities/model_params.py
src/demand_forecast_source/entities/split_params.py
src/demand_forecast_source/entities/train_pipeline_params.py
src/demand_forecast_source/entities/validation_params.py
src/demand_forecast_source/entities/__pycache__/feature_params.cpython-38.pyc
src/demand_forecast_source/entities/__pycache__/model_params.cpython-38.pyc
src/demand_forecast_source/entities/__pycache__/split_params.cpython-38.pyc
src/demand_forecast_source/entities/__pycache__/train_pipeline_params.cpython-38.pyc
src/demand_forecast_source/features/.gitkeep
src/demand_forecast_source/features/AddFeatures.py
src/demand_forecast_source/features/AddTargets.py
src/demand_forecast_source/features/__init__.py
src/demand_forecast_source/features/build_sku_by_day.py
src/demand_forecast_source/features/build_transformer.py
src/demand_forecast_source/features/__pycache__/AddFeatures.cpython-38.pyc
src/demand_forecast_source/features/__pycache__/AddTargets.cpython-38.pyc
src/demand_forecast_source/features/__pycache__/__init__.cpython-38.pyc
src/demand_forecast_source/features/__pycache__/build_sku_by_day.cpython-38.pyc
src/demand_forecast_source/features/__pycache__/build_transformer.cpython-38.pyc
src/demand_forecast_source/inference/__init__.py
src/demand_forecast_source/inference/make_request.py
