Metadata-Version: 2.1
Name: demand-forecast-source
Version: 1.0.3.17
Summary: This is lib-predicts for demand forecast based on machine learning
Home-page: https://github.com/Edipool/DemandForecast
Author: Eduard Poliakov
Author-email: ya.polykov@gmail.com
License: MIT
Platform: UNKNOWN
Classifier: Programming Language :: Python :: 3.8
